keralagram/__init__.py
keralagram/bot.py
keralagram/dispatcher.py
keralagram/filters.py
keralagram/errors/__init__.py
keralagram/types/__init__.py
keralagram/types/inline/__init__.py
keralagram/types/inline/chosen_inline_result.py
keralagram/types/inline/inline_keyboard_button.py
keralagram/types/inline/inline_keyboard_markup.py
keralagram/types/inline/login_url.py
keralagram/types/messages_and_medias/__init__.py
keralagram/types/messages_and_medias/animation.py
keralagram/types/messages_and_medias/audio.py
keralagram/types/messages_and_medias/contact.py
keralagram/types/messages_and_medias/document.py
keralagram/types/messages_and_medias/location.py
keralagram/types/messages_and_medias/message.py
keralagram/types/messages_and_medias/message_entity.py
keralagram/types/messages_and_medias/photo_size.py
keralagram/types/messages_and_medias/pinnedmessage.py
keralagram/types/messages_and_medias/video.py
keralagram/types/messages_and_medias/video_note.py
keralagram/types/messages_and_medias/voice.py
keralagram/types/polls/__init__.py
keralagram/types/polls/poll.py
keralagram/types/polls/poll_answer.py
keralagram/types/polls/poll_option.py
keralagram/types/users_and_chats/__init__.py
keralagram/types/users_and_chats/chat.py
keralagram/types/users_and_chats/user.py
keralagram/types/users_and_chats/user_profile_photos.py
keralagram/utils/__init__.py
keralagram/utils/utils.py
keralagram-0.1.9.dist-info/METADATA
keralagram-0.1.9.dist-info/WHEEL
keralagram-0.1.9.dist-info/top_level.txt
keralagram-0.1.9.dist-info/RECORD
