Metadata-Version: 2.1
Name: keralagram
Version: 0.1.9
Summary: Asynchronous Python API for building Telegram bots
Home-page: https://github.com/KeralaBots/Keralagram
Author: Anand P S
Author-email: anandpskerala@gmail.com
License: MIT
Project-URL: Community, https://t.me/KeralasBots
Project-URL: Source, https://github.com/KeralasBots/Keralagram
Keywords: telegram asyncio bot
Platform: UNKNOWN
Classifier: Development Status :: 2 - Pre-Alpha
Classifier: Intended Audience :: Developers
Classifier: Natural Language :: English
Classifier: License :: OSI Approved :: GNU Lesser General Public License v3 or later (LGPLv3+)
Classifier: Operating System :: OS Independent
Classifier: Programming Language :: Python
Classifier: Programming Language :: Python :: 3
Classifier: Programming Language :: Python :: 3.6
Classifier: Programming Language :: Python :: 3.7
Classifier: Programming Language :: Python :: 3.8
Classifier: Programming Language :: Python :: 3.9
Classifier: Topic :: Software Development
Classifier: Topic :: Software Development :: Libraries
Requires-Dist: aiohttp
Requires-Dist: pyaes (==1.6.1)
Requires-Dist: pysocks (==1.7.1)
Requires-Dist: async-lru (==1.0.2)
